memscope/__init__.py
memscope/__main__.py
memscope/cli.py
memscope/core.py
memscope/simulator.py
memscope/visualizer.py
memscope-0.1.2.dist-info/licenses/LICENSE
memscope-0.1.2.dist-info/METADATA
memscope-0.1.2.dist-info/WHEEL
memscope-0.1.2.dist-info/top_level.txt
memscope-0.1.2.dist-info/RECORD
