Metadata-Version: 2.4
Name: memscope
Version: 0.1.2
Summary: Analyze and simulate dynamic memory usage in C/C++ code
Author-email: Miriam Kanner <m0534147159@email.com>
License: MIT
License-File: LICENSE
Requires-Dist: matplotlib
Dynamic: license-file
